{
  "categories": [
    { "id": "resources", "name": "Resources" },
    { "id": "components", "name": "Components" },
    { "id": "buildables", "name": "Buildables" },
    { "id": "crafters", "name": "Crafters" },
    { "id": "power-generators", "name": "Power Generators" }
  ],
  "items": [
    {
      "id": "adv-machinery-parts",
      "name": "Advanced Machinery Parts",
      "category": "components"
    },
    {
      "id": "adv-smelter",
      "name": "Advanced Smelter",
      "category": "crafters",
      "craftingTimeMultiplier": { "numerator": 2.0, "denominator": 3.0 }
    },
    {
      "id": "assembler-i",
      "name": "Assembler I",
      "category": "crafters",
      "craftingTimeMultiplier": 1.0
    },
    {
      "id": "assembler-ii",
      "name": "Assembler II",
      "category": "crafters",
      "craftingTimeMultiplier": { "numerator": 2.0, "denominator": 3.0 }
    },
    {
      "id": "assembler-iii",
      "name": "Assembler III",
      "category": "crafters",
      "craftingTimeMultiplier": 0.5
    },
    {
      "id": "biomass-burner",
      "name": "Biomass Burner",
      "category": "power-generators",
      "size": "1x2x1",
      "power": 600.0,
      "efficiency": 0.7
    },
    {
      "id": "boiler",
      "name": "Boiler",
      "category": "buildables",
      "size": "1x1x1"
    },
    {
      "id": "building-block",
      "name": "Building Block",
      "category": "buildables",
      "size": "1x1x1"
    },
    {
      "id": "burner-generator",
      "name": "Burner Generator",
      "category": "power-generators",
      "size": "4x6x4",
      "power": 1800.0,
      "efficiency": 0.8
    },
    {
      "id": "casting-machine",
      "name": "Casting Machine",
      "category": "crafters",
      "craftingTimeMultiplier": 1.0
    },
    {
      "id": "character",
      "name": "Character",
      "category": "crafters",
      "craftingTimeMultiplier": { "numerator": 1.0, "denominator": 3.0 }
    },
    {
      "id": "circuit-board",
      "name": "Circuit Board",
      "category": "components"
    },
    {
      "id": "conveyor-i",
      "name": "Conveyor I",
      "category": "buildables",
      "size": "1x1x1"
    },
    {
      "id": "conveyor-ii",
      "name": "Conveyor II",
      "category": "buildables",
      "size": "1x1x1"
    },
    {
      "id": "conveyor-iii",
      "name": "Conveyor III",
      "category": "buildables",
      "size": "1x1x1"
    },
    {
      "id": "conveyor-balancer-i",
      "name": "Conveyor Balancer I",
      "category": "buildables",
      "size": "2x1x2"
    },
    {
      "id": "conveyor-balancer-ii",
      "name": "Conveyor Balancer II",
      "category": "buildables",
      "size": "2x1x2"
    },
    {
      "id": "conveyor-balancer-iii",
      "name": "Conveyor Balancer III",
      "category": "buildables",
      "size": "2x1x2"
    },
    {
      "id": "conveyor-slope-i",
      "name": "Conveyor Slope I",
      "category": "buildables",
      "size": "2x2x1"
    },
    {
      "id": "conveyor-slope-ii",
      "name": "Conveyor Slope II",
      "category": "buildables",
      "size": "2x2x1"
    },
    {
      "id": "conveyor-slope-iii",
      "name": "Conveyor Slope III",
      "category": "buildables",
      "size": "2x2x1"
    },
    {
      "id": "crusher-i",
      "name": "Crusher I",
      "category": "crafters",
      "craftingTimeMultiplier": 1.0
    },
    {
      "id": "crusher-ii",
      "name": "Crusher II",
      "category": "crafters",
      "craftingTimeMultiplier": 0.5
    },
    {
      "id": "drone-miner-i",
      "name": "Drone Miner I",
      "category": "buildables",
      "size": "2x2x2",
      "power": -200.0
    },
    {
      "id": "drone-miner-ii",
      "name": "Drone Miner II",
      "category": "buildables",
      "size": "2x2x2",
      "power": 0.0
    },
    {
      "id": "electronic-components",
      "name": "Electronic Components",
      "category": "components"
    },
    {
      "id": "elevator",
      "name": "Elevator",
      "category": "buildables",
      "size": "5x3x6"
    },
    {
      "id": "emergency-beacon",
      "name": "Emergency Beacon",
      "category": "buildables",
      "size": "5x5x5"
    },
    {
      "id": "escalator",
      "name": "Escalator",
      "category": "buildables",
      "size": "varies"
    },
    {
      "id": "freight-elevator",
      "name": "Freight Elevator",
      "category": "buildables",
      "size": "4x?x3"
    },
    {
      "id": "gravel",
      "name": "Gravel",
      "category": "components"
    },
    {
      "id": "igni-fuel-rod",
      "name": "Ignium Fuel Rod",
      "category": "components"
    },
    {
      "id": "igni-ore",
      "name": "Ignium Ore",
      "category": "components"
    },
    {
      "id": "igni-ore-rubble",
      "name": "Ignium Ore Rubble",
      "category": "resources"
    },
    {
      "id": "igni-powder",
      "name": "Ignium Powder",
      "category": "components"
    },
    {
      "id": "ladder",
      "name": "Ladder",
      "category": "buildables",
      "size": "1x1x1"
    },
    {
      "id": "loader",
      "name": "Loader",
      "category": "buildables",
      "size": "2x2x1",
      "power": -5.0
    },
    {
      "id": "loader-2-lane",
      "name": "Loader, 2nd Lane",
      "category": "buildables",
      "size": "3x2x1",
      "power": -10.0
    },
    {
      "id": "loader-3-lane",
      "name": "Loader, 3rd Lane",
      "category": "buildables",
      "size": "4x2x1",
      "power": -15.0
    },
    {
      "id": "loader-filter",
      "name": "Filter Loader",
      "category": "buildables",
      "size": "2x2x1",
      "power": -5.0
    },
    {
      "id": "machinery-parts",
      "name": "Machinery Parts",
      "category": "components"
    },
    {
      "id": "pipe",
      "name": "Pipe",
      "category": "buildables",
      "size": "1x1x1"
    },
    {
      "id": "pipe-intake",
      "name": "Pipe Intake",
      "category": "buildables",
      "size": "1x1x1"
    },
    {
      "id": "pump",
      "name": "Pump",
      "category": "buildables",
      "size": "2x2x1",
      "power": -200.0
    },
    {
      "id": "shipping-pad-small",
      "name": "Shipping Pad (Small)",
      "category": "buildables",
      "size": "20x13x10"
    },
    {
      "id": "shipping-pad-medium",
      "name": "Shipping Pad (Medium)",
      "category": "buildables",
      "size": "31x19x27"
    },
    {
      "id": "smelter-small",
      "name": "Smelter (Small)",
      "category": "crafters",
      "craftingTimeMultiplier": 1.0
    },
    {
      "id": "space-station-terminal",
      "name": "Space Station Terminal",
      "category": "buildables",
      "size": "2x4x2",
      "power": -50.0
    },
    {
      "id": "stairs",
      "name": "Stairs",
      "category": "buildables",
      "size": "varies"
    },
    {
      "id": "steam-turbine",
      "name": "Steam Turbine",
      "category": "power-generators",
      "size": "12x6x5",
      "power": 3600.0,
      "efficiency": 1.0
    },
    {
      "id": "steel-beams",
      "name": "Steel Beams",
      "category": "components"
    },
    {
      "id": "tech-molten",
      "name": "Molten Technum",
      "category": "components"
    },
    {
      "id": "tech-ore",
      "name": "Technum Ore",
      "category": "components"
    },
    {
      "id": "tech-ore-rubble",
      "name": "Technum Ore Rubble",
      "category": "resources"
    },
    {
      "id": "tech-rods",
      "name": "Technum Rods",
      "category": "components"
    },
    {
      "id": "walkway",
      "name": "Walkway",
      "category": "buildables",
      "size": "varies"
    },
    {
      "id": "xeno-igni-ore-blend",
      "category": "components",
      "name": "Xenoferrite-Ignium Ore Blend"
    },
    {
      "id": "xeno-molten",
      "category": "components",
      "name": "Molten Xenoferrite"
    },
    {
      "id": "xeno-ore",
      "category": "components",
      "name": "Xenoferrite Ore"
    },
    {
      "id": "xeno-ore-rubble",
      "category": "resources",
      "name": "Xenoferrite Ore Rubble"
    },
    {
      "id": "xeno-plates",
      "category": "components",
      "name": "Xenoferrite Plates"
    }
  ],
  "recipes": [
    {
      "id": "adv-machinery-parts",
      "name": "Advanced Machinery Parts",
      "category": "components",
      "time": 1.5,
      "in": { "machinery-parts": 2, "steel-beams": 1 },
      "out": { "adv-machinery-parts": 1 },
      "crafters": [
        "character",
        "assembler-i",
        "assembler-ii",
        "assembler-iii"
      ]
    },
    {
      "id": "drone-miner-i",
      "name": "Drone Miner I",
      "category": "crafters",
      "time": 5.0,
      "in": { "xeno-plates": 10, "machinery-parts": 8, "electronic-components": 6 },
      "out": { "drone-miner-i": 1 },
      "crafters": [
        "character",
        "assembler-i",
        "assembler-iii",
        "assembler-ii"
      ]
    },
    {
      "id": "drone-miner-ii",
      "name": "Drone Miner II",
      "category": "crafters",
      "time": 7.5,
      "in": { "drone-miner-i": 1, "adv-machinery-parts": 10, "circuit-board": 4 },
      "out": { "drone-miner-ii": 1 },
      "crafters": [
        "character",
        "assembler-i",
        "assembler-ii",
        "assembler-iii"
      ]
    },
    {
      "id": "machinery-parts",
      "name": "Machinery Parts",
      "category": "components",
      "time": 1.5,
      "in": { "xeno-plates": 1 },
      "out": { "machinery-parts": 1 },
      "crafters": [
        "character",
        "assembler-i",
        "assembler-ii",
        "assembler-iii"
      ]
    },
    {
      "id": "xeno-plates-t1",
      "name": "Xenoferrite Plates (Tier 1)",
      "category": "components",
      "time": 3.0,
      "in": { "xeno-ore-rubble": 1 },
      "out": { "xeno-plates": 1 },
      "crafters": [
        "smelter-small",
        "adv-smelter"
      ]
    },
    {
      "id": "xeno-plates-t2",
      "name": "Xenoferrite Plates (Tier 2)",
      "category": "components",
      "time": 6.0,
      "in": { "xeno-ore": 2 },
      "out": { "xeno-plates": 3 },
      "crafters": [
        "smelter-small",
        "adv-smelter"
      ]
    },
    {
      "id": "xeno-plates-t3",
      "name": "Xenoferrite Plates (Tier 3)",
      "category": "components",
      "time": 7.5,
      "in": { "xeno-molten": 15 },
      "out": { "xeno-plates": 5 },
      "crafters": [
        "casting-machine"
      ]
    },
    {
      "id": "tech-rods-t1",
      "name": "Technum Rods (Tier 1)",
      "category": "components",
      "time": 3.0,
      "in": { "tech-ore-rubble": 1 },
      "out": { "tech-rods": 1 },
      "crafters": [
        "smelter-small",
        "adv-smelter"
      ]
    },
    {
      "id": "tech-rods-t2",
      "name": "Technum Rods (Tier 2)",
      "category": "components",
      "time": 6.0,
      "in": { "tech-ore": 2 },
      "out": { "tech-rods": 3 },
      "crafters": [
        "smelter-small",
        "adv-smelter"
      ]
    },
    {
      "id": "tech-rods-t3",
      "name": "Technum Rods (Tier 3)",
      "category": "components",
      "time": 7.5,
      "in": { "tech-molten": 15 },
      "out": { "tech-rods": 5 },
      "crafters": [
        "casting-machine"
      ]
    }
  ],
  "technologies": [
    {
      "id": "steel-smelting",
      "name": "Steel Smelting",
      "category": "technologies",
      "technology": {
        "prerequisites": ["automatic-metallurgy"],
        "unlockedRecipes": ["steel"]
      }
    }
  ]
}